model/sram.v
module sram
  (input [7:0]   addr,
   input         cen,
   input         wen,
   input         oen,
   inout [7:0]   dq
  );

`ifdef DEBUG
  localparam DEBUG_ON = 1;
`else
  localparam DEBUG_ON = 0;
`endif

  localparam TOOLCHAIN = 1;

  //----------------------------------------------------------------------
  // Instruction Set
  //----------------------------------------------------------------------
  //Arithmetic and Logic
  localparam     AND   = 4'h0;            // A = A & B
  localparam     OR    = 4'h1;            // A = A |  B
  localparam     INV   = 4'h2;            // A = ~A
  localparam     ADD   = 4'h3;            // A = A + B

  // Data Movement from and to memory
  localparam     LDI   = 4'h4;            // A = {A[3:0], instr[3:0]}
  localparam     LDM   = 4'h5;            // A = mem(M)
  localparam     STM   = 4'h6;            // mem(M) = A

  // Data Movement within registers
  localparam     SWAB  = 4'h8;            // A <-> B
  localparam     SWMB  = 4'h9;            // M <-> B
  localparam     CPPA  = 4'hA;            // A <-- P
  localparam     CPAM  = 4'hB;            // M <-- A

  // Jumps and branching
  localparam     JU    = 4'hC;            // Always   P <-> M
  localparam     JE    = 4'hD;            // A == B ? P <-> M
  localparam     JL    = 4'hE;            // A < B  ? P <-> M
  localparam     JG    = 4'hF;            // A > B  ? P <-> M

  reg  [7:0]   addr_reg;
  reg  [7:0]   sram [0:255];
  reg          hizen;
  wire [7:0]   q;

  assign q  = sram[addr];
  assign dq = hizen ? q : 8'hZZ;

  initial
    begin
      if (TOOLCHAIN)
        begin
          $readmemh("program.mem", sram);
        end
      else
        begin
          sram[  0] = {LDI,  4'h3};  // LDI 3
          sram[  1] = {LDI,  4'h4};  // LDI 4
          sram[  2] = {SWAB, 4'h0};  // SWAB
          sram[  3] = {LDI,  4'h1};  // LDI 1
          sram[  4] = {LDI,  4'h2};  // LDI 2
          sram[  5] = {ADD,  4'h0};  // ADD
          sram[  6] = {SWAB, 4'h0};  // SWAB
          sram[  7] = {LDI,  4'h7};  // LDI 7
          sram[  8] = {LDI,  4'hF};  // LDI F
          sram[  9] = {CPAM, 4'h0};  // CPAM
          sram[ 10] = {SWAB, 4'h0};  // SWAB
          sram[ 11] = {STM,  4'h0};  // STM  (M[7F] = 46)
          sram[ 12] = {LDI,  4'h0};  // LDI 0
          sram[ 13] = {LDI,  4'h0};  // LDI 0
          sram[ 14] = {LDM,  4'h0};  // LDM  (A = M[7F] = 46)

          sram[ 15] = {LDI,  4'h1};  // LDI 1
          sram[ 16] = {LDI,  4'h2};  // LDI 2 (12 hex is 18 decimal)
          sram[ 17] = {CPAM, 4'h0};  // CPAM
          sram[ 18] = {JU,   4'h0};  // JU (to this address - 0x12 = 0d18)

          // This is a forever loop or halt
        end
    end // initial begin

  always // @(cen or oen or wen)
    begin
      hizen <= 1'b0;
      wait ((cen == 1'b0) || (wen == 1'b0));

      if (cen == 1'b1)     // CE initiated cycle
        begin
          wait(cen == 1'b0);
          addr_reg <= addr;  // Flop address on falling edge of CE

          if (DEBUG_ON)
            begin
              $display("At time %0t: CE Initiated Write cycle", $stime);
            end

          wait ((cen == 1'b1) || (wen == 1'b1));

          if (DEBUG_ON)
            begin
              if (wen == 1'b1)
                begin
                  $display("At time %0t: WE Terminated Write Cycle, mem[%x] = %x", $stime, addr_reg, dq);
                end
              else
                begin
                  $display("At time %0t: CE Terminated Write Cycle, mem[%x] = %x", $stime, addr_reg, dq);
                end
            end

          sram[addr_reg] = dq;
          wait ((cen == 1'b1) && (wen == 1'b1));
        end

      else                 // WE initiated cycle
        begin
          wait ((wen == 1'b0) || (oen == 1'b0));

          if (wen == 1'b0) // Write cycle
            begin
              addr_reg <= addr;  // Flop address on falling edge of CE

              if (DEBUG_ON)
                begin
                  $display("At time %0t: WE Initiated Write cycle", $stime);
                end

              wait ((cen == 1'b1) || (wen == 1'b1));

              if (DEBUG_ON)
                begin
                  if (wen == 1'b1)
                    begin
                      $display("At time %0t: WE Terminated Write Cycle, mem[%x] = %x", $stime, addr_reg, dq);
                    end
                  else
                    begin
                      $display("At time %0t: CE Terminated Write Cycle, mem[%x] = %x", $stime, addr_reg, dq);
                    end
                end

              sram[addr_reg] = dq;
              wait ((cen == 1'b1) && (wen == 1'b1));
            end // if (wen == 1'b0)

          else
            begin
              wait (oen == 1'b0);
              hizen <= 1'b1;
              if (DEBUG_ON)
                begin
                  $display("At time %0t: READ mem[%x] = %x", $stime, addr, q);
                end
              wait ((oen == 1'b1) || (cen == 1'b1));
              hizen <= 1'b0;
              wait ((oen == 1'b1) && (cen == 1'b1));
            end // else: !if(wen == 1'b0)
        end // else: !if(wen == 1'b0)
    end // always begin

endmodule // sram

model/tinycpu.v
module tinycpu
  (input       clk,
   input       reset
  );

  //----------------------------------------------------------------------
  // Instruction Set
  //----------------------------------------------------------------------
  //Arithmetic and Logic
  localparam     AND   = 4'h0;            // A = A & B
  localparam     OR    = 4'h1;            // A = A |  B
  localparam     INV   = 4'h2;            // A = ~A
  localparam     ADD   = 4'h3;            // A = A + B

  // Data Movement from and to memory
  localparam     LDI   = 4'h4;            // A = {A[3:0], instr[3:0]}
  localparam     LDM   = 4'h5;            // A = mem(M)
  localparam     STM   = 4'h6;            // mem(M) = A

  // Data Movement within registers
  localparam     SWAB  = 4'h8;            // A <-> B
  localparam     SWMB  = 4'h9;            // M <-> B
  localparam     CPPA  = 4'hA;            // A <-- P
  localparam     CPAM  = 4'hB;            // M <-- A

  // Jumps and branching
  localparam     JU    = 4'hC;            // Always   P <-> M
  localparam     JE    = 4'hD;            // A == B ? P <-> M
  localparam     JL    = 4'hE;            // A < B  ? P <-> M
  localparam     JG    = 4'hF;            // A > B  ? P <-> M

  //----------------------------------------------------------------------
  // FSM States
  //----------------------------------------------------------------------
  localparam     IDLE    = 3'd0;
  localparam     FETCH   = 3'd1;
  localparam     EXEC    = 3'd2;
  localparam     MEMACC1 = 3'd3;
  localparam     MEMACC2 = 3'd4;
  localparam     MEMACC3 = 3'd5;

  //----------------------------------------------------------------------
  // CPU registers
  //----------------------------------------------------------------------
  reg [7:0]    rA;
  reg [7:0]    rB;
  reg [7:0]    rM;
  reg [7:0]    rP;

  //----------------------------------------------------------------------
  // Other regs and wires
  //----------------------------------------------------------------------
  reg          den;
  reg          cen;
  reg          wen;
  reg          oen;
  reg [7:0]    addr;
  reg [2:0]    exec_state;
  reg [7:0]    instr;

  // Memory data bus - has tristate control
  wire [7:0]   dq = den ? rA : 8'hZZ;

  //----------------------------------------------------------------------
  // Control FSM and Instruction decode and execute (all in one)
  //----------------------------------------------------------------------
  always @(posedge clk or negedge reset)
    if (reset == 1'b0)
      begin
        rA         <= 8'h00;
        rB         <= 8'h00;
        rM         <= 8'h00;
        rP         <= 8'h00;

        cen        <= 1'b1;
        oen        <= 1'b1;
        wen        <= 1'b1;
        den        <= 1'b0;
        instr      <= 8'h00;
        addr       <= 8'h00;

        exec_state <= IDLE;
      end

    else
      begin
        case (exec_state)
          IDLE:
            begin
              cen        <= 1'b0;
              oen        <= 1'b0;
              wen        <= 1'b1;
              addr       <= rP;
              den        <= 1'b0;
              exec_state <= FETCH;
            end

          FETCH:
            begin
              cen        <= 1'b1;
              oen        <= 1'b1;
              wen        <= 1'b1;
              addr       <= rP;
              den        <= 1'b0;
              instr      <= dq;
              rP         <= rP + 1'b1;
              exec_state <= EXEC;
            end

          EXEC:
            begin
              addr <= rP;
              exec_state <= IDLE;

              case (instr[7:4])
                //----------------------------------------------------------
                // Arithmetic
                //----------------------------------------------------------
                AND:
                  begin
                    rA <= rA & rB;
                  end

                OR:
                  begin
                    rA <= rA | rB;
                  end

                INV:
                  begin
                    rA <= ~rA;
                  end

                ADD:
                  begin
                    rA <= rA + rB;
                  end

                //----------------------------------------------------------
                // Data Movement from and to memory
                //----------------------------------------------------------
                LDI:
                  begin
                    rA <= {rA[3:0], instr[3:0]};
                  end

                LDM:
                  begin
                    cen        <= 1'b0;
                    oen        <= 1'b0;
                    wen        <= 1'b1;
                    den        <= 1'b0;
                    addr       <= rM;
                    exec_state <= MEMACC1;
                  end

                STM:
                  begin
                    cen        <= 1'b1;
                    oen        <= 1'b1;
                    wen        <= 1'b1;
                    den        <= 1'b1;
                    addr       <= rM;
                    exec_state <= MEMACC1;
                  end

                //----------------------------------------------------------
                // Data Movement within registers
                //----------------------------------------------------------
                SWAB:
                  begin
                    rA <= rB;
                    rB <= rA;
                  end

                SWMB:
                  begin
                    rB <= rM;
                    rM <= rB;
                  end

                CPPA:
                  begin
                    rA <= rP;
                  end

                CPAM:
                  begin
                    rM <= rA;
                  end

                //----------------------------------------------------------
                // Branch
                //----------------------------------------------------------
                JU:  // Unconditional Jump
                  begin
                    // rM <= rP;
                    rP <= rM;
                  end

                JE:  // Jump on equal flag
                  begin
                    if (rA == rB)
                      begin
                        // rM <= rP;
                        rP <= rM;
                      end
                  end

                JL:  // Jump on less than flag
                  begin
                    if (rA < rB)
                      begin
                        // rM <= rP;
                        rP <= rM;
                      end
                  end

                JG:  // Jump on greater than flag
                  begin
                    if (rA > rB)
                      begin
                        // rM <= rP;
                        rP <= rM;
                      end
                  end

              endcase // case (instr)

            end // case: EXEC

          MEMACC1:
            begin
              if (den == 1'b0)
                begin
                  rA         <= dq;
                  addr       <= rP;
                  exec_state <= IDLE;
                end
              else
                begin
                  cen        <= 1'b0;
                  oen        <= 1'b1;
                  wen        <= 1'b0;
                  exec_state <= MEMACC2;
                end // else: !if(den == 1'b0)
            end

          MEMACC2:
            begin
              cen        <= 1'b1;
              wen        <= 1'b1;
              exec_state <= MEMACC3;
            end

          MEMACC3:
            begin
              addr       <= rP;
              den        <= 1'b0;
              exec_state <= IDLE;
            end

        endcase // case (exec_state)

      end // else: !if(!reset)

  //----------------------------------------------------------------------
  // SRAM
  //----------------------------------------------------------------------
  sram sram
    (.addr(addr),
     .cen(cen),
     .wen(wen),
     .oen(oen),
     .dq(dq)
     );


endmodule

model/tinycpu_test.v
module tinycpu_test;

  reg clk;
  reg reset;

  initial
    begin
      $dumpvars;
      clk <= 1'b0;
      reset <= 1'b0;
      #10;
      reset <= 1'b1;
    end

  always
    begin
      #5;
      clk <= 1'b1;
      #5;
      clk <= 1'b0;
    end

  always @(posedge clk)
    begin
      if (cpumodel.exec_state == 3'd2
          && cpumodel.instr[7:6] == 2'b11
          && (cpumodel.rP - 1) == cpumodel.rM
          && reset == 1'b1)
        begin
          $display("Detected forever loop, halting CPU.");
          $finish;
        end
      if (cpumodel.exec_state == 3'd0 && reset == 1'b1)
        begin
          $display("A = %x, B = %x, M = %x, P = %x",
                   cpumodel.rA, cpumodel.rB, cpumodel.rM, cpumodel.rP);
        end
    end

  tinycpu cpumodel
    (.clk(clk),
     .reset(reset)
    );

endmodule // tinycpu_test

run/model_dump.vcd
$date
	Sat Jun  3 21:28:24 2023
$end
$version
	Icarus Verilog
$end
$timescale
	1s
$end
$scope module tinycpu_test $end
$var reg 1 ! clk $end
$var reg 1 " reset $end
$scope module cpumodel $end
$var wire 1 ! clk $end
$var wire 8 # dq [7:0] $end
$var wire 1 " reset $end
$var reg 8 $ addr [7:0] $end
$var reg 1 % cen $end
$var reg 1 & den $end
$var reg 3 ' exec_state [2:0] $end
$var reg 8 ( instr [7:0] $end
$var reg 1 ) oen $end
$var reg 8 * rA [7:0] $end
$var reg 8 + rB [7:0] $end
$var reg 8 , rM [7:0] $end
$var reg 8 - rP [7:0] $end
$var reg 1 . wen $end
$scope module sram $end
$var wire 8 / addr [7:0] $end
$var wire 1 % cen $end
$var wire 8 0 dq [7:0] $end
$var wire 1 ) oen $end
$var wire 8 1 q [7:0] $end
$var wire 1 . wen $end
$var reg 8 2 addr_reg [7:0] $end
$var reg 1 3 hizen $end
$upscope $end
$upscope $end
$upscope $end
$enddefinitions $end
#0
$dumpvars
03
bx 2
b1000000 1
bz 0
b0 /
1.
b0 -
b0 ,
b0 +
b0 *
1)
b0 (
b0 '
0&
1%
b0 $
bz #
0"
0!
$end
#5
1!
#10
0!
1"
#15
b1000000 #
b1000000 0
13
b1 '
0)
0%
1!
#20
0!
#25
bz #
bz 0
03
b10 '
b1 -
b1000000 (
1)
1%
1!
#30
0!
#35
b0 '
b1000010 1
b1 $
b1 /
1!
#40
0!
#45
b1000010 #
b1000010 0
13
b1 '
0)
0%
1!
#50
0!
#55
bz #
bz 0
03
b10 '
b10 -
b1000010 (
1)
1%
1!
#60
0!
#65
b10 *
b0 '
b10000000 1
b10 $
b10 /
1!
#70
0!
#75
b10000000 #
b10000000 0
13
b1 '
0)
0%
1!
#80
0!
#85
bz #
bz 0
03
b10 '
b11 -
b10000000 (
1)
1%
1!
#90
0!
#95
b10 +
b0 *
b0 '
b10100000 1
b11 $
b11 /
1!
#100
0!
#105
b10100000 #
b10100000 0
13
b1 '
0)
0%
1!
#110
0!
#115
bz #
bz 0
03
b10 '
b100 -
b10100000 (
1)
1%
1!
#120
0!
#125
b100 *
b0 '
b110000 1
b100 $
b100 /
1!
#130
0!
#135
b110000 #
b110000 0
13
b1 '
0)
0%
1!
#140
0!
#145
bz #
bz 0
03
b10 '
b101 -
b110000 (
1)
1%
1!
#150
0!
#155
b110 *
b0 '
b10110000 1
b101 $
b101 /
1!
#160
0!
#165
b10110000 #
b10110000 0
13
b1 '
0)
0%
1!
#170
0!
#175
bz #
bz 0
03
b10 '
b110 -
b10110000 (
1)
1%
1!
#180
0!
#185
b110 ,
b0 '
b10000000 1
b110 $
b110 /
1!
#190
0!
#195
b10000000 #
b10000000 0
13
b1 '
0)
0%
1!
#200
0!
#205
bz #
bz 0
03
b10 '
b111 -
b10000000 (
1)
1%
1!
#210
0!
#215
b110 +
b10 *
b0 '
b1000000 1
b111 $
b111 /
1!
#220
0!
#225
b1000000 #
b1000000 0
13
b1 '
0)
0%
1!
#230
0!
#235
bz #
bz 0
03
b10 '
b1000 -
b1000000 (
1)
1%
1!
#240
0!
#245
b100000 *
b0 '
b1000001 1
b1000 $
b1000 /
1!
#250
0!
#255
b1000001 #
b1000001 0
13
b1 '
0)
0%
1!
#260
0!
#265
bz #
bz 0
03
b10 '
b1001 -
b1000001 (
1)
1%
1!
#270
0!
#275
b1 *
b0 '
b10000000 1
b1001 $
b1001 /
1!
#280
0!
#285
b10000000 #
b10000000 0
13
b1 '
0)
0%
1!
#290
0!
#295
bz #
bz 0
03
b10 '
b1010 -
b10000000 (
1)
1%
1!
#300
0!
#305
b1 +
b110 *
b0 '
b110000 1
b1010 $
b1010 /
1!
#310
0!
#315
b110000 #
b110000 0
13
b1 '
0)
0%
1!
#320
0!
#325
bz #
bz 0
03
b10 '
b1011 -
b110000 (
1)
1%
1!
#330
0!
#335
b111 *
b0 '
b11110000 1
b1011 $
b1011 /
1!
#340
0!
#345
b11110000 #
b11110000 0
13
b1 '
0)
0%
1!
#350
0!
#355
bz #
bz 0
03
b10 '
b1100 -
b11110000 (
1)
1%
1!
#360
0!
#365
b110 -
b0 '
b1000000 1
b1100 $
b1100 /
1!
#370
0!
#375
b10000000 #
b10000000 0
13
b1 '
b10000000 1
b110 $
b110 /
0)
0%
1!
#380
0!
#385
bz #
bz 0
03
b10 '
b111 -
b10000000 (
1)
1%
1!
#390
0!
#395
b111 +
b1 *
b0 '
b1000000 1
b111 $
b111 /
1!
#400
0!
#405
b1000000 #
b1000000 0
13
b1 '
0)
0%
1!
#410
0!
#415
bz #
bz 0
03
b10 '
b1000 -
b1000000 (
1)
1%
1!
#420
0!
#425
b10000 *
b0 '
b1000001 1
b1000 $
b1000 /
1!
#430
0!
#435
b1000001 #
b1000001 0
13
b1 '
0)
0%
1!
#440
0!
#445
bz #
bz 0
03
b10 '
b1001 -
b1000001 (
1)
1%
1!
#450
0!
#455
b1 *
b0 '
b10000000 1
b1001 $
b1001 /
1!
#460
0!
#465
b10000000 #
b10000000 0
13
b1 '
0)
0%
1!
#470
0!
#475
bz #
bz 0
03
b10 '
b1010 -
b10000000 (
1)
1%
1!
#480
0!
#485
b1 +
b111 *
b0 '
b110000 1
b1010 $
b1010 /
1!
#490
0!
#495
b110000 #
b110000 0
13
b1 '
0)
0%
1!
#500
0!
#505
bz #
bz 0
03
b10 '
b1011 -
b110000 (
1)
1%
1!
#510
0!
#515
b1000 *
b0 '
b11110000 1
b1011 $
b1011 /
1!
#520
0!
#525
b11110000 #
b11110000 0
13
b1 '
0)
0%
1!
#530
0!
#535
bz #
bz 0
03
b10 '
b1100 -
b11110000 (
1)
1%
1!
#540
0!
#545
b110 -
b0 '
b1000000 1
b1100 $
b1100 /
1!
#550
0!
#555
b10000000 #
b10000000 0
13
b1 '
b10000000 1
b110 $
b110 /
0)
0%
1!
#560
0!
#565
bz #
bz 0
03
b10 '
b111 -
b10000000 (
1)
1%
1!
#570
0!
#575
b1000 +
b1 *
b0 '
b1000000 1
b111 $
b111 /
1!
#580
0!
#585
b1000000 #
b1000000 0
13
b1 '
0)
0%
1!
#590
0!
#595
bz #
bz 0
03
b10 '
b1000 -
b1000000 (
1)
1%
1!
#600
0!
#605
b10000 *
b0 '
b1000001 1
b1000 $
b1000 /
1!
#610
0!
#615
b1000001 #
b1000001 0
13
b1 '
0)
0%
1!
#620
0!
#625
bz #
bz 0
03
b10 '
b1001 -
b1000001 (
1)
1%
1!
#630
0!
#635
b1 *
b0 '
b10000000 1
b1001 $
b1001 /
1!
#640
0!
#645
b10000000 #
b10000000 0
13
b1 '
0)
0%
1!
#650
0!
#655
bz #
bz 0
03
b10 '
b1010 -
b10000000 (
1)
1%
1!
#660
0!
#665
b1 +
b1000 *
b0 '
b110000 1
b1010 $
b1010 /
1!
#670
0!
#675
b110000 #
b110000 0
13
b1 '
0)
0%
1!
#680
0!
#685
bz #
bz 0
03
b10 '
b1011 -
b110000 (
1)
1%
1!
#690
0!
#695
b1001 *
b0 '
b11110000 1
b1011 $
b1011 /
1!
#700
0!
#705
b11110000 #
b11110000 0
13
b1 '
0)
0%
1!
#710
0!
#715
bz #
bz 0
03
b10 '
b1100 -
b11110000 (
1)
1%
1!
#720
0!
#725
b110 -
b0 '
b1000000 1
b1100 $
b1100 /
1!
#730
0!
#735
b10000000 #
b10000000 0
13
b1 '
b10000000 1
b110 $
b110 /
0)
0%
1!
#740
0!
#745
bz #
bz 0
03
b10 '
b111 -
b10000000 (
1)
1%
1!
#750
0!
#755
b1001 +
b1 *
b0 '
b1000000 1
b111 $
b111 /
1!
#760
0!
#765
b1000000 #
b1000000 0
13
b1 '
0)
0%
1!
#770
0!
#775
bz #
bz 0
03
b10 '
b1000 -
b1000000 (
1)
1%
1!
#780
0!
#785
b10000 *
b0 '
b1000001 1
b1000 $
b1000 /
1!
#790
0!
#795
b1000001 #
b1000001 0
13
b1 '
0)
0%
1!
#800
0!
#805
bz #
bz 0
03
b10 '
b1001 -
b1000001 (
1)
1%
1!
#810
0!
#815
b1 *
b0 '
b10000000 1
b1001 $
b1001 /
1!
#820
0!
#825
b10000000 #
b10000000 0
13
b1 '
0)
0%
1!
#830
0!
#835
bz #
bz 0
03
b10 '
b1010 -
b10000000 (
1)
1%
1!
#840
0!
#845
b1 +
b1001 *
b0 '
b110000 1
b1010 $
b1010 /
1!
#850
0!
#855
b110000 #
b110000 0
13
b1 '
0)
0%
1!
#860
0!
#865
bz #
bz 0
03
b10 '
b1011 -
b110000 (
1)
1%
1!
#870
0!
#875
b1010 *
b0 '
b11110000 1
b1011 $
b1011 /
1!
#880
0!
#885
b11110000 #
b11110000 0
13
b1 '
0)
0%
1!
#890
0!
#895
bz #
bz 0
03
b10 '
b1100 -
b11110000 (
1)
1%
1!
#900
0!
#905
b110 -
b0 '
b1000000 1
b1100 $
b1100 /
1!
#910
0!
#915
b10000000 #
b10000000 0
13
b1 '
b10000000 1
b110 $
b110 /
0)
0%
1!
#920
0!
#925
bz #
bz 0
03
b10 '
b111 -
b10000000 (
1)
1%
1!
#930
0!
#935
b1010 +
b1 *
b0 '
b1000000 1
b111 $
b111 /
1!
#940
0!
#945
b1000000 #
b1000000 0
13
b1 '
0)
0%
1!
#950
0!
#955
bz #
bz 0
03
b10 '
b1000 -
b1000000 (
1)
1%
1!
#960
0!
#965
b10000 *
b0 '
b1000001 1
b1000 $
b1000 /
1!
#970
0!
#975
b1000001 #
b1000001 0
13
b1 '
0)
0%
1!
#980
0!
#985
bz #
bz 0
03
b10 '
b1001 -
b1000001 (
1)
1%
1!
#990
0!
#995
b1 *
b0 '
b10000000 1
b1001 $
b1001 /
1!
#1000
0!
#1005
b10000000 #
b10000000 0
13
b1 '
0)
0%
1!
#1010
0!
#1015
bz #
bz 0
03
b10 '
b1010 -
b10000000 (
1)
1%
1!
#1020
0!
#1025
b1 +
b1010 *
b0 '
b110000 1
b1010 $
b1010 /
1!
#1030
0!
#1035
b110000 #
b110000 0
13
b1 '
0)
0%
1!
#1040
0!
#1045
bz #
bz 0
03
b10 '
b1011 -
b110000 (
1)
1%
1!
#1050
0!
#1055
b1011 *
b0 '
b11110000 1
b1011 $
b1011 /
1!
#1060
0!
#1065
b11110000 #
b11110000 0
13
b1 '
0)
0%
1!
#1070
0!
#1075
bz #
bz 0
03
b10 '
b1100 -
b11110000 (
1)
1%
1!
#1080
0!
#1085
b110 -
b0 '
b1000000 1
b1100 $
b1100 /
1!
#1090
0!
#1095
b10000000 #
b10000000 0
13
b1 '
b10000000 1
b110 $
b110 /
0)
0%
1!
#1100
0!
#1105
bz #
bz 0
03
b10 '
b111 -
b10000000 (
1)
1%
1!
#1110
0!
#1115
b1011 +
b1 *
b0 '
b1000000 1
b111 $
b111 /
1!
#1120
0!
#1125
b1000000 #
b1000000 0
13
b1 '
0)
0%
1!
#1130
0!
#1135
bz #
bz 0
03
b10 '
b1000 -
b1000000 (
1)
1%
1!
#1140
0!
#1145
b10000 *
b0 '
b1000001 1
b1000 $
b1000 /
1!
#1150
0!
#1155
b1000001 #
b1000001 0
13
b1 '
0)
0%
1!
#1160
0!
#1165
bz #
bz 0
03
b10 '
b1001 -
b1000001 (
1)
1%
1!
#1170
0!
#1175
b1 *
b0 '
b10000000 1
b1001 $
b1001 /
1!
#1180
0!
#1185
b10000000 #
b10000000 0
13
b1 '
0)
0%
1!
#1190
0!
#1195
bz #
bz 0
03
b10 '
b1010 -
b10000000 (
1)
1%
1!
#1200
0!
#1205
b1 +
b1011 *
b0 '
b110000 1
b1010 $
b1010 /
1!
#1210
0!
#1215
b110000 #
b110000 0
13
b1 '
0)
0%
1!
#1220
0!
#1225
bz #
bz 0
03
b10 '
b1011 -
b110000 (
1)
1%
1!
#1230
0!
#1235
b1100 *
b0 '
b11110000 1
b1011 $
b1011 /
1!
#1240
0!
#1245
b11110000 #
b11110000 0
13
b1 '
0)
0%
1!
#1250
0!
#1255
bz #
bz 0
03
b10 '
b1100 -
b11110000 (
1)
1%
1!
#1260
0!
#1265
b110 -
b0 '
b1000000 1
b1100 $
b1100 /
1!
#1270
0!
#1275
b10000000 #
b10000000 0
13
b1 '
b10000000 1
b110 $
b110 /
0)
0%
1!
#1280
0!
#1285
bz #
bz 0
03
b10 '
b111 -
b10000000 (
1)
1%
1!
#1290
0!
#1295
b1100 +
b1 *
b0 '
b1000000 1
b111 $
b111 /
1!
#1300
0!
#1305
b1000000 #
b1000000 0
13
b1 '
0)
0%
1!
#1310
0!
#1315
bz #
bz 0
03
b10 '
b1000 -
b1000000 (
1)
1%
1!
#1320
0!
#1325
b10000 *
b0 '
b1000001 1
b1000 $
b1000 /
1!
#1330
0!
#1335
b1000001 #
b1000001 0
13
b1 '
0)
0%
1!
#1340
0!
#1345
bz #
bz 0
03
b10 '
b1001 -
b1000001 (
1)
1%
1!
#1350
0!
#1355
b1 *
b0 '
b10000000 1
b1001 $
b1001 /
1!
#1360
0!
#1365
b10000000 #
b10000000 0
13
b1 '
0)
0%
1!
#1370
0!
#1375
bz #
bz 0
03
b10 '
b1010 -
b10000000 (
1)
1%
1!
#1380
0!
#1385
b1 +
b1100 *
b0 '
b110000 1
b1010 $
b1010 /
1!
#1390
0!
#1395
b110000 #
b110000 0
13
b1 '
0)
0%
1!
#1400
0!
#1405
bz #
bz 0
03
b10 '
b1011 -
b110000 (
1)
1%
1!
#1410
0!
#1415
b1101 *
b0 '
b11110000 1
b1011 $
b1011 /
1!
#1420
0!
#1425
b11110000 #
b11110000 0
13
b1 '
0)
0%
1!
#1430
0!
#1435
bz #
bz 0
03
b10 '
b1100 -
b11110000 (
1)
1%
1!
#1440
0!
#1445
b110 -
b0 '
b1000000 1
b1100 $
b1100 /
1!
#1450
0!
#1455
b10000000 #
b10000000 0
13
b1 '
b10000000 1
b110 $
b110 /
0)
0%
1!
#1460
0!
#1465
bz #
bz 0
03
b10 '
b111 -
b10000000 (
1)
1%
1!
#1470
0!
#1475
b1101 +
b1 *
b0 '
b1000000 1
b111 $
b111 /
1!
#1480
0!
#1485
b1000000 #
b1000000 0
13
b1 '
0)
0%
1!
#1490
0!
#1495
bz #
bz 0
03
b10 '
b1000 -
b1000000 (
1)
1%
1!
#1500
0!
#1505
b10000 *
b0 '
b1000001 1
b1000 $
b1000 /
1!
#1510
0!
#1515
b1000001 #
b1000001 0
13
b1 '
0)
0%
1!
#1520
0!
#1525
bz #
bz 0
03
b10 '
b1001 -
b1000001 (
1)
1%
1!
#1530
0!
#1535
b1 *
b0 '
b10000000 1
b1001 $
b1001 /
1!
#1540
0!
#1545
b10000000 #
b10000000 0
13
b1 '
0)
0%
1!
#1550
0!
#1555
bz #
bz 0
03
b10 '
b1010 -
b10000000 (
1)
1%
1!
#1560
0!
#1565
b1 +
b1101 *
b0 '
b110000 1
b1010 $
b1010 /
1!
#1570
0!
#1575
b110000 #
b110000 0
13
b1 '
0)
0%
1!
#1580
0!
#1585
bz #
bz 0
03
b10 '
b1011 -
b110000 (
1)
1%
1!
#1590
0!
#1595
b1110 *
b0 '
b11110000 1
b1011 $
b1011 /
1!
#1600
0!
#1605
b11110000 #
b11110000 0
13
b1 '
0)
0%
1!
#1610
0!
#1615
bz #
bz 0
03
b10 '
b1100 -
b11110000 (
1)
1%
1!
#1620
0!
#1625
b110 -
b0 '
b1000000 1
b1100 $
b1100 /
1!
#1630
0!
#1635
b10000000 #
b10000000 0
13
b1 '
b10000000 1
b110 $
b110 /
0)
0%
1!
#1640
0!
#1645
bz #
bz 0
03
b10 '
b111 -
b10000000 (
1)
1%
1!
#1650
0!
#1655
b1110 +
b1 *
b0 '
b1000000 1
b111 $
b111 /
1!
#1660
0!
#1665
b1000000 #
b1000000 0
13
b1 '
0)
0%
1!
#1670
0!
#1675
bz #
bz 0
03
b10 '
b1000 -
b1000000 (
1)
1%
1!
#1680
0!
#1685
b10000 *
b0 '
b1000001 1
b1000 $
b1000 /
1!
#1690
0!
#1695
b1000001 #
b1000001 0
13
b1 '
0)
0%
1!
#1700
0!
#1705
bz #
bz 0
03
b10 '
b1001 -
b1000001 (
1)
1%
1!
#1710
0!
#1715
b1 *
b0 '
b10000000 1
b1001 $
b1001 /
1!
#1720
0!
#1725
b10000000 #
b10000000 0
13
b1 '
0)
0%
1!
#1730
0!
#1735
bz #
bz 0
03
b10 '
b1010 -
b10000000 (
1)
1%
1!
#1740
0!
#1745
b1 +
b1110 *
b0 '
b110000 1
b1010 $
b1010 /
1!
#1750
0!
#1755
b110000 #
b110000 0
13
b1 '
0)
0%
1!
#1760
0!
#1765
bz #
bz 0
03
b10 '
b1011 -
b110000 (
1)
1%
1!
#1770
0!
#1775
b1111 *
b0 '
b11110000 1
b1011 $
b1011 /
1!
#1780
0!
#1785
b11110000 #
b11110000 0
13
b1 '
0)
0%
1!
#1790
0!
#1795
bz #
bz 0
03
b10 '
b1100 -
b11110000 (
1)
1%
1!
#1800
0!
#1805
b110 -
b0 '
b1000000 1
b1100 $
b1100 /
1!
#1810
0!
#1815
b10000000 #
b10000000 0
13
b1 '
b10000000 1
b110 $
b110 /
0)
0%
1!
#1820
0!
#1825
bz #
bz 0
03
b10 '
b111 -
b10000000 (
1)
1%
1!
#1830
0!
#1835
b1111 +
b1 *
b0 '
b1000000 1
b111 $
b111 /
1!
#1840
0!
#1845
b1000000 #
b1000000 0
13
b1 '
0)
0%
1!
#1850
0!
#1855
bz #
bz 0
03
b10 '
b1000 -
b1000000 (
1)
1%
1!
#1860
0!
#1865
b10000 *
b0 '
b1000001 1
b1000 $
b1000 /
1!
#1870
0!
#1875
b1000001 #
b1000001 0
13
b1 '
0)
0%
1!
#1880
0!
#1885
bz #
bz 0
03
b10 '
b1001 -
b1000001 (
1)
1%
1!
#1890
0!
#1895
b1 *
b0 '
b10000000 1
b1001 $
b1001 /
1!
#1900
0!
#1905
b10000000 #
b10000000 0
13
b1 '
0)
0%
1!
#1910
0!
#1915
bz #
bz 0
03
b10 '
b1010 -
b10000000 (
1)
1%
1!
#1920
0!
#1925
b1 +
b1111 *
b0 '
b110000 1
b1010 $
b1010 /
1!
#1930
0!
#1935
b110000 #
b110000 0
13
b1 '
0)
0%
1!
#1940
0!
#1945
bz #
bz 0
03
b10 '
b1011 -
b110000 (
1)
1%
1!
#1950
0!
#1955
b10000 *
b0 '
b11110000 1
b1011 $
b1011 /
1!
#1960
0!
#1965
b11110000 #
b11110000 0
13
b1 '
0)
0%
1!
#1970
0!
#1975
bz #
bz 0
03
b10 '
b1100 -
b11110000 (
1)
1%
1!
#1980
0!
#1985
b110 -
b0 '
b1000000 1
b1100 $
b1100 /
1!
#1990
0!
#1995
b10000000 #
b10000000 0
13
b1 '
b10000000 1
b110 $
b110 /
0)
0%
1!
#2000
0!
#2005
bz #
bz 0
03
b10 '
b111 -
b10000000 (
1)
1%
1!
#2010
0!
#2015
b10000 +
b1 *
b0 '
b1000000 1
b111 $
b111 /
1!
#2020
0!
#2025
b1000000 #
b1000000 0
13
b1 '
0)
0%
1!
#2030
0!
